{
  "$defs": {
    "AdaptiveCFL": {
      "additionalProperties": false,
      "description": "Adaptive CFL for time stepping component\n\n\nParameters\n----------\ntype : typing.Literal['adaptive'] = adaptive\n        min : <class 'float'> = 0.1\n        max : typing.Optional[typing.Annotated[float, Gt(gt=0)]] = None\n        max_relative_change : typing.Optional[typing.Annotated[float, Gt(gt=0)]] = None\n        convergence_limiting_factor : typing.Optional[typing.Annotated[float, Gt(gt=0)]] = None\n    ",
      "properties": {
        "type": {
          "const": "adaptive",
          "default": "adaptive",
          "enum": [
            "adaptive"
          ],
          "title": "Type",
          "type": "string"
        },
        "min": {
          "default": 0.1,
          "exclusiveMinimum": 0.0,
          "title": "Min",
          "type": "number"
        },
        "max": {
          "anyOf": [
            {
              "exclusiveMinimum": 0.0,
              "type": "number"
            },
            {
              "type": "null"
            }
          ],
          "default": null,
          "title": "Max"
        },
        "max_relative_change": {
          "anyOf": [
            {
              "exclusiveMinimum": 0.0,
              "type": "number"
            },
            {
              "type": "null"
            }
          ],
          "default": null,
          "title": "Max Relative Change"
        },
        "convergence_limiting_factor": {
          "anyOf": [
            {
              "exclusiveMinimum": 0.0,
              "type": "number"
            },
            {
              "type": "null"
            }
          ],
          "default": null,
          "title": "Convergence Limiting Factor"
        }
      },
      "title": "AdaptiveCFL",
      "type": "object"
    },
    "RampCFL": {
      "additionalProperties": false,
      "description": "Ramp CFL for time stepping component\n\n\nParameters\n----------\ntype : typing.Literal['ramp'] = ramp\n        initial : typing.Optional[typing.Annotated[float, Gt(gt=0)]] = None\n        final : typing.Optional[typing.Annotated[float, Gt(gt=0)]] = None\n        ramp_steps : typing.Optional[typing.Annotated[int, Gt(gt=0)]] = None\n    ",
      "properties": {
        "type": {
          "const": "ramp",
          "default": "ramp",
          "enum": [
            "ramp"
          ],
          "title": "Type",
          "type": "string"
        },
        "initial": {
          "anyOf": [
            {
              "exclusiveMinimum": 0.0,
              "type": "number"
            },
            {
              "type": "null"
            }
          ],
          "default": null,
          "title": "Initial"
        },
        "final": {
          "anyOf": [
            {
              "exclusiveMinimum": 0.0,
              "type": "number"
            },
            {
              "type": "null"
            }
          ],
          "default": null,
          "title": "Final"
        },
        "ramp_steps": {
          "anyOf": [
            {
              "exclusiveMinimum": 0,
              "type": "integer"
            },
            {
              "type": "null"
            }
          ],
          "default": null,
          "title": "Ramp Steps"
        }
      },
      "title": "RampCFL",
      "type": "object"
    }
  },
  "additionalProperties": false,
  "description": "Unsteady time stepping component\n\n\nParameters\n----------\norder_of_accuracy : typing.Literal[1, 2] = 2\n        type_name : typing.Literal['Unsteady'] = Unsteady\n        max_pseudo_steps : <class 'int'> = 100\n    Maximum pseudo steps within one physical step.\nsteps : <class 'int'>\n    Number of physical steps.\nstep_size : <class 'flow360.component.simulation.unit_system._Constrained'>\n    Time step size in physical step marching,\nCFL : typing.Union[flow360.component.simulation.time_stepping.time_stepping.RampCFL, flow360.component.simulation.time_stepping.time_stepping.AdaptiveCFL] = AdaptiveCFL(type='adaptive', min=0.1, max=1000000.0, max_relative_change=50.0, convergence_limiting_factor=1.0)\n    ",
  "properties": {
    "order_of_accuracy": {
      "default": 2,
      "enum": [
        1,
        2
      ],
      "title": "Order Of Accuracy",
      "type": "integer"
    },
    "type_name": {
      "const": "Unsteady",
      "default": "Unsteady",
      "enum": [
        "Unsteady"
      ],
      "title": "Type Name",
      "type": "string"
    },
    "max_pseudo_steps": {
      "default": 100,
      "description": "Maximum pseudo steps within one physical step.",
      "exclusiveMinimum": 0,
      "maximum": 100000,
      "title": "Max Pseudo Steps",
      "type": "integer"
    },
    "steps": {
      "description": "Number of physical steps.",
      "exclusiveMinimum": 0,
      "title": "Steps",
      "type": "integer"
    },
    "step_size": {
      "description": "Time step size in physical step marching,",
      "properties": {
        "value": {
          "exclusiveMinimum": 0,
          "type": "number"
        },
        "units": {
          "dimension": "time",
          "enum": [
            "s"
          ],
          "type": "string"
        }
      },
      "title": "Step Size"
    },
    "CFL": {
      "anyOf": [
        {
          "$ref": "#/$defs/RampCFL"
        },
        {
          "$ref": "#/$defs/AdaptiveCFL"
        }
      ],
      "default": {
        "type": "adaptive",
        "min": 0.1,
        "max": 1000000.0,
        "maxRelativeChange": 50.0,
        "convergenceLimitingFactor": 1.0
      },
      "title": "Cfl"
    }
  },
  "required": [
    "steps",
    "step_size"
  ],
  "title": "Unsteady",
  "type": "object"
}